stata2python/__init__.py
stata2python/funcs.py
stata2python/.ipynb_checkpoints/funcs-checkpoint.py
stata2python-0.0.16.dist-info/METADATA
stata2python-0.0.16.dist-info/WHEEL
stata2python-0.0.16.dist-info/licenses/LICENSE
stata2python-0.0.16.dist-info/RECORD
