Metadata-Version: 2.1
Name: stata2python
Version: 0.0.16
Summary: Takes in Stata commands and outputs their Python equivalent
Project-URL: Repository, https://github.com/rohanjha123/data-h195/tree/main/creating_package
Project-URL: Functions, https://github.com/rohanjha123/data-h195/blob/main/creating_package/src/stata2python/funcs.py
Project-URL: Issues, https://github.com/rohanjha123/data-h195/issues
Author-email: Rohan Jha <rohan.jha@berkeley.edu>
License-File: LICENSE
Classifier: Development Status :: 3 - Alpha
Classifier: License :: OSI Approved :: MIT License
Classifier: Operating System :: OS Independent
Classifier: Programming Language :: Python :: 2
Classifier: Programming Language :: Python :: 3
Requires-Python: >=2.7
Requires-Dist: regex
